{
  "resolvedId": "/media/linux/833cfef0-7984-46f2-8f58-ee0be3a5d0782/DATA/XPS-DATA/DEV/WORKSPACE/PROJECTS/PARTNERSHIPS/IMPERAMAX/OFFERS/nuxt-restaurant-management-system/src/components/dashboard/utils/tables/book/Main.vue",
  "transforms": [
    {
      "name": "vite:load-fallback",
      "result": "<script setup>\n\ndefineProps({\n  menu: Array,\n  columns: String,\n})\n\n\nconst bookingStore = useBookingStore()\nlet { bookings } = bookingStore\n\nfunction getMonthName(monthNumber) {\n  const date = new Date();\n  date.setMonth(monthNumber);\n\n  return date.toLocaleString('en-US', { month: 'short' });\n}\n\nfunction datesaregay(date_string){\n  var date = new Date(date_string)\n  var result = \"\" + (date.getDay() + 1) + \"/\" + (date.getMonth() + 1) + \"/\" + date.getFullYear() + \", \" + date.toLocaleTimeString() \n  //var result = \"\" + date.getFullYear() + getMonthName(date.getMonth()) + date.getDay()\n\nconsole.log(result)\n  return result\n}\n</script>\n\n\n<template>\n  <!-- BUTTON BookingsCreateModal -->   \n      <DashboardBookingsModalsCreate />\n    <UTable :columns=\"columns\" :rows='bookings' :sort=\"{ column: 'title' }\" >\n    <template #edit-data=\"{row}\">\n      <DashboardBookingsModalsEdit :bookingitem=\"row\" />\n      </template>\n    <template #datetime-data=\"{row}\">\n      {{ datesaregay(row.datetime) }}\n    </template>\n    <template #delete-data=\"{row}\">\n      <DashboardBookingsModalsDelete :bookingitem=\"row\" />\n      </template>\n\n  </UTable>\n\n</template>    \n",
      "start": 1717261250767,
      "end": 1717261251096,
      "sourcemaps": null
    },
    {
      "name": "nuxt:layer-aliasing",
      "start": 1717261251096,
      "end": 1717261251096,
      "order": "pre"
    },
    {
      "name": "nuxt:server-devonly:transform",
      "start": 1717261251096,
      "end": 1717261251096,
      "order": "pre"
    },
    {
      "name": "nuxt:client-fallback-auto-id",
      "start": 1717261251096,
      "end": 1717261251096,
      "order": "pre"
    },
    {
      "name": "vite:css",
      "start": 1717261251096,
      "end": 1717261251096,
      "order": "normal"
    },
    {
      "name": "vite:esbuild",
      "start": 1717261251097,
      "end": 1717261251097,
      "order": "normal"
    },
    {
      "name": "vite:json",
      "start": 1717261251097,
      "end": 1717261251097,
      "order": "normal"
    },
    {
      "name": "vite:worker",
      "start": 1717261251097,
      "end": 1717261251097,
      "order": "normal"
    },
    {
      "name": "vite:vue",
      "result": "import { resolveComponent as _resolveComponent, createVNode as _createVNode, unref as _unref, toDisplayString as _toDisplayString, createTextVNode as _createTextVNode, withCtx as _withCtx, Fragment as _Fragment, openBlock as _openBlock, createElementBlock as _createElementBlock } from \"vue\"\n\n\nconst _sfc_main = {\n  __name: 'Main',\n  props: {\n  menu: Array,\n  columns: String,\n},\n  setup(__props) {\n\n\n\n\n\nconst bookingStore = useBookingStore()\nlet { bookings } = bookingStore\n\nfunction getMonthName(monthNumber) {\n  const date = new Date();\n  date.setMonth(monthNumber);\n\n  return date.toLocaleString('en-US', { month: 'short' });\n}\n\nfunction datesaregay(date_string){\n  var date = new Date(date_string)\n  var result = \"\" + (date.getDay() + 1) + \"/\" + (date.getMonth() + 1) + \"/\" + date.getFullYear() + \", \" + date.toLocaleTimeString() \n  //var result = \"\" + date.getFullYear() + getMonthName(date.getMonth()) + date.getDay()\n\nconsole.log(result)\n  return result\n}\n\nreturn (_ctx, _cache) => {\n  const _component_DashboardBookingsModalsCreate = _resolveComponent(\"DashboardBookingsModalsCreate\")\n  const _component_DashboardBookingsModalsEdit = _resolveComponent(\"DashboardBookingsModalsEdit\")\n  const _component_DashboardBookingsModalsDelete = _resolveComponent(\"DashboardBookingsModalsDelete\")\n  const _component_UTable = _resolveComponent(\"UTable\")\n\n  return (_openBlock(), _createElementBlock(_Fragment, null, [\n    _createVNode(_component_DashboardBookingsModalsCreate),\n    _createVNode(_component_UTable, {\n      columns: __props.columns,\n      rows: _unref(bookings),\n      sort: { column: 'title' }\n    }, {\n      \"edit-data\": _withCtx(({row}) => [\n        _createVNode(_component_DashboardBookingsModalsEdit, { bookingitem: row }, null, 8, [\"bookingitem\"])\n      ]),\n      \"datetime-data\": _withCtx(({row}) => [\n        _createTextVNode(_toDisplayString(datesaregay(row.datetime)), 1)\n      ]),\n      \"delete-data\": _withCtx(({row}) => [\n        _createVNode(_component_DashboardBookingsModalsDelete, { bookingitem: row }, null, 8, [\"bookingitem\"])\n      ]),\n      _: 1\n    }, 8, [\"columns\", \"rows\"])\n  ], 64))\n}\n}\n\n}\n\n\n\nexport default _sfc_main",
      "start": 1717261251097,
      "end": 1717261251099,
      "order": "normal",
      "sourcemaps": {
        "mappings": ""
      }
    },
    {
      "name": "vite:vue-jsx",
      "start": 1717261251099,
      "end": 1717261251099,
      "order": "normal"
    },
    {
      "name": "replace",
      "start": 1717261251099,
      "end": 1717261251099,
      "order": "normal"
    },
    {
      "name": "nuxt:remove-plugin-metadata",
      "start": 1717261251099,
      "end": 1717261251099,
      "order": "normal"
    },
    {
      "name": "nuxt:chunk-error",
      "start": 1717261251099,
      "end": 1717261251099,
      "order": "normal"
    },
    {
      "name": "nuxt:components:imports",
      "start": 1717261251099,
      "end": 1717261251099,
      "order": "normal"
    },
    {
      "name": "replace",
      "start": 1717261251099,
      "end": 1717261251099,
      "order": "normal"
    },
    {
      "name": "ssr-styles",
      "start": 1717261251099,
      "end": 1717261251099,
      "order": "normal"
    },
    {
      "name": "vite:define",
      "start": 1717261251099,
      "end": 1717261251099,
      "order": "normal"
    },
    {
      "name": "vite:css-post",
      "start": 1717261251099,
      "end": 1717261251099,
      "order": "normal"
    },
    {
      "name": "vite:build-html",
      "start": 1717261251099,
      "end": 1717261251099,
      "order": "normal"
    },
    {
      "name": "vite:worker-import-meta-url",
      "start": 1717261251099,
      "end": 1717261251099,
      "order": "normal"
    },
    {
      "name": "vite:asset-import-meta-url",
      "start": 1717261251099,
      "end": 1717261251099,
      "order": "normal"
    },
    {
      "name": "commonjs",
      "start": 1717261251099,
      "end": 1717261251099,
      "order": "normal"
    },
    {
      "name": "vite:dynamic-import-vars",
      "start": 1717261251099,
      "end": 1717261251099,
      "order": "normal"
    },
    {
      "name": "vite:import-glob",
      "start": 1717261251099,
      "end": 1717261251099,
      "order": "normal"
    },
    {
      "name": "nuxt:composable-keys",
      "start": 1717261251099,
      "end": 1717261251099,
      "order": "post"
    },
    {
      "name": "nuxt:imports-transform",
      "result": "import { useBookingStore } from '/media/linux/833cfef0-7984-46f2-8f58-ee0be3a5d0782/DATA/XPS-DATA/DEV/WORKSPACE/PROJECTS/PARTNERSHIPS/IMPERAMAX/OFFERS/nuxt-restaurant-management-system/src/stores/bookings.ts';\nimport { resolveComponent as _resolveComponent, createVNode as _createVNode, unref as _unref, toDisplayString as _toDisplayString, createTextVNode as _createTextVNode, withCtx as _withCtx, Fragment as _Fragment, openBlock as _openBlock, createElementBlock as _createElementBlock } from \"vue\"\n\n\nconst _sfc_main = {\n  __name: 'Main',\n  props: {\n  menu: Array,\n  columns: String,\n},\n  setup(__props) {\n\n\n\n\n\nconst bookingStore = useBookingStore()\nlet { bookings } = bookingStore\n\nfunction getMonthName(monthNumber) {\n  const date = new Date();\n  date.setMonth(monthNumber);\n\n  return date.toLocaleString('en-US', { month: 'short' });\n}\n\nfunction datesaregay(date_string){\n  var date = new Date(date_string)\n  var result = \"\" + (date.getDay() + 1) + \"/\" + (date.getMonth() + 1) + \"/\" + date.getFullYear() + \", \" + date.toLocaleTimeString() \n  //var result = \"\" + date.getFullYear() + getMonthName(date.getMonth()) + date.getDay()\n\nconsole.log(result)\n  return result\n}\n\nreturn (_ctx, _cache) => {\n  const _component_DashboardBookingsModalsCreate = _resolveComponent(\"DashboardBookingsModalsCreate\")\n  const _component_DashboardBookingsModalsEdit = _resolveComponent(\"DashboardBookingsModalsEdit\")\n  const _component_DashboardBookingsModalsDelete = _resolveComponent(\"DashboardBookingsModalsDelete\")\n  const _component_UTable = _resolveComponent(\"UTable\")\n\n  return (_openBlock(), _createElementBlock(_Fragment, null, [\n    _createVNode(_component_DashboardBookingsModalsCreate),\n    _createVNode(_component_UTable, {\n      columns: __props.columns,\n      rows: _unref(bookings),\n      sort: { column: 'title' }\n    }, {\n      \"edit-data\": _withCtx(({row}) => [\n        _createVNode(_component_DashboardBookingsModalsEdit, { bookingitem: row }, null, 8, [\"bookingitem\"])\n      ]),\n      \"datetime-data\": _withCtx(({row}) => [\n        _createTextVNode(_toDisplayString(datesaregay(row.datetime)), 1)\n      ]),\n      \"delete-data\": _withCtx(({row}) => [\n        _createVNode(_component_DashboardBookingsModalsDelete, { bookingitem: row }, null, 8, [\"bookingitem\"])\n      ]),\n      _: 1\n    }, 8, [\"columns\", \"rows\"])\n  ], 64))\n}\n}\n\n}\n\n\n\nexport default _sfc_main",
      "start": 1717261251099,
      "end": 1717261251100,
      "order": "post",
      "sourcemaps": {
        "version": 3,
        "sources": [
          ""
        ],
        "names": [],
        "mappings": ";AAAA,CAAC,CAAC,CAAC,CAAC,CAAC,CAAC,CAAC,CAAC,CAAC,CAAC,CAAC,CAAC,CAAC,CAAC,CAAC,CAAC,CAAC,CAAC,CAAC,CAAC,CAAC,CAAC,CAAC,CAAC,CAAC,CAAC,CAAC,CAAC,CAAC,CAAC,CAAC,CAAC,CAAC,CAAC,CAAC,CAAC,CAAC,CAAC,CAAC,CAAC,CAAC,CAAC,CAAC,CAAC,CAAC,CAAC,CAAC,CAAC,CAAC,CAAC,CAAC,CAAC,CAAC,CAAC,CAAC,CAAC,CAAC,CAAC,CAAC,CAAC,CAAC,CAAC,CAAC,CAAC,CAAC,CAAC,CAAC,CAAC,CAAC,CAAC,CAAC,CAAC,CAAC,CAAC,CAAC,CAAC,CAAC,CAAC,CAAC,CAAC,CAAC,CAAC,CAAC,CAAC,CAAC,CAAC,CAAC,CAAC,CAAC,CAAC,CAAC,CAAC,CAAC,CAAC,CAAC,CAAC,CAAC,CAAC,CAAC,CAAC,CAAC,CAAC,CAAC,CAAC,CAAC,CAAC,CAAC,CAAC,CAAC,CAAC,CAAC,CAAC,CAAC,CAAC,CAAC,CAAC,CAAC,CAAC,CAAC,CAAC,CAAC,CAAC,CAAC,CAAC,CAAC,CAAC,CAAC,CAAC,CAAC,CAAC,CAAC,CAAC,CAAC,CAAC,CAAC,CAAC,CAAC,CAAC,CAAC,CAAC,CAAC,CAAC,CAAC,CAAC,CAAC,CAAC,CAAC,CAAC,CAAC,CAAC,CAAC,CAAC,CAAC,CAAC,CAAC,CAAC,CAAC,CAAC,CAAC,CAAC,CAAC,CAAC,CAAC,CAAC,CAAC,CAAC,CAAC,CAAC,CAAC,CAAC,CAAC,CAAC,CAAC,CAAC,CAAC,CAAC,CAAC,CAAC,CAAC,CAAC,CAAC,CAAC,CAAC,CAAC,CAAC,CAAC,CAAC,CAAC,CAAC,CAAC,CAAC,CAAC,CAAC,CAAC,CAAC,CAAC,CAAC,CAAC,CAAC,CAAC,CAAC,CAAC,CAAC,CAAC,CAAC,CAAC,CAAC,CAAC,CAAC,CAAC,CAAC,CAAC,CAAC,CAAC,CAAC,CAAC,CAAC,CAAC,CAAC,CAAC,CAAC,CAAC,CAAC,CAAC,CAAC,CAAC,CAAC,CAAC,CAAC,CAAC,CAAC,CAAC,CAAC,CAAC,CAAC,CAAC,CAAC,CAAC,CAAC,CAAC,CAAC,CAAC,CAAC,CAAC,CAAC,CAAC,CAAC,CAAC,CAAC,CAAC,CAAC,CAAC,CAAC,CAAC,CAAC,CAAC,CAAC,CAAC,CAAC,CAAC,CAAC,CAAC,CAAC,CAAC,CAAC,CAAC,CAAC,CAAC,CAAC,CAAC,CAAC,CAAC,CAAC,CAAC,CAAC,CAAC,CAAC,CAAC,CAAC,CAAC,CAAC,CAAC,CAAC,CAAC,CAAC,CAAC,CAAC,CAAC,CAAC,CAAC,CAAC;AACnS;AACA;AACA,CAAC,CAAC,CAAC,CAAC,CAAC,CAAC,CAAC,CAAC,CAAC,CAAC,CAAC,CAAC,CAAC,CAAC,CAAC,CAAC,CAAC,CAAC,CAAC;AACnB,CAAC,CAAC,CAAC,CAAC,CAAC,CAAC,CAAC,CAAC,CAAC,CAAC,CAAC,CAAC,CAAC,CAAC,CAAC,CAAC,CAAC;AACjB,CAAC,CAAC,CAAC,CAAC,CAAC,CAAC,CAAC,CAAC,CAAC,CAAC;AACV,CAAC,CAAC,CAAC,CAAC,CAAC,CAAC,CAAC,CAAC,CAAC,CAAC,CAAC,CAAC,CAAC,CAAC;AACd,CAAC,CAAC,CAAC,CAAC,CAAC,CAAC,CAAC,CAAC,CAAC,CAAC,CAAC,CAAC,CAAC,CAAC,CAAC,CAAC,CAAC,CAAC;AAClB,CAAC,CAAC;AACF,CAAC,CAAC,CAAC,CAAC,CAAC,CAAC,CAAC,CAAC,CAAC,CAAC,CAAC,CAAC,CAAC,CAAC,CAAC,CAAC,CAAC,CAAC;AAClB;AACA;AACA;AACA;AACA;AACA,CAAC,CAAC,CAAC,CAAC,CAAC,CAAC,CAAC,CAAC,CAAC,CAAC,CAAC,CAAC,CAAC,CAAC,CAAC,CAAC,CAAC,CAAC,CAAC,CAAC,CAAC,CAAC,CAAC,CAAC,CAAC,CAAC,CAAC,CAAC,CAAC,CAAC,CAAC,CAAC,CAAC,CAAC,CAAC,CAAC,CAAC,CAAC;AACtC,CAAC,CAAC,CAAC,CAAC,CAAC,CAAC,CAAC,CAAC,CAAC,CAAC,CAAC,CAAC,CAAC,CAAC,CAAC,CAAC,CAAC,CAAC,CAAC,CAAC,CAAC,CAAC,CAAC,CAAC,CAAC,CAAC,CAAC,CAAC,CAAC,CAAC,CAAC;AAC/B;AACA,CAAC,CAAC,CAAC,CAAC,CAAC,CAAC,CAAC,CAAC,CAAC,CAAC,CAAC,CAAC,CAAC,CAAC,CAAC,CAAC,CAAC,CAAC,CAAC,CAAC,CAAC,CAAC,CAAC,CAAC,CAAC,CAAC,CAAC,CAAC,CAAC,CAAC,CAAC,CAAC,CAAC,CAAC,CAAC,CAAC;AACpC,CAAC,CAAC,CAAC,CAAC,CAAC,CAAC,CAAC,CAAC,CAAC,CAAC,CAAC,CAAC,CAAC,CAAC,CAAC,CAAC,CAAC,CAAC,CAAC,CAAC,CAAC,CAAC,CAAC,CAAC,CAAC,CAAC;AAC1B,CAAC,CAAC,CAAC,CAAC,CAAC,CAAC,CAAC,CAAC,CAAC,CAAC,CAAC,CAAC,CAAC,CAAC,CAAC,CAAC,CAAC,CAAC,CAAC,CAAC,CAAC,CAAC,CAAC,CAAC,CAAC,CAAC,CAAC,CAAC,CAAC;AAC7B;AACA,CAAC,CAAC,CAAC,CAAC,CAAC,CAAC,CAAC,CAAC,CAAC,CAAC,CAAC,CAAC,CAAC,CAAC,CAAC,CAAC,CAAC,CAAC,CAAC,CAAC,CAAC,CAAC,CAAC,CAAC,CAAC,CAAC,CAAC,CAAC,CAAC,CAAC,CAAC,CAAC,CAAC,CAAC,CAAC,CAAC,CAAC,CAAC,CAAC,CAAC,CAAC,CAAC,CAAC,CAAC,CAAC,CAAC,CAAC,CAAC,CAAC,CAAC,CAAC,CAAC,CAAC,CAAC,CAAC,CAAC,CAAC,CAAC;AAC1D,CAAC;AACD;AACA,CAAC,CAAC,CAAC,CAAC,CAAC,CAAC,CAAC,CAAC,CAAC,CAAC,CAAC,CAAC,CAAC,CAAC,CAAC,CAAC,CAAC,CAAC,CAAC,CAAC,CAAC,CAAC,CAAC,CAAC,CAAC,CAAC,CAAC,CAAC,CAAC,CAAC,CAAC,CAAC,CAAC,CAAC;AAClC,CAAC,CAAC,CAAC,CAAC,CAAC,CAAC,CAAC,CAAC,CAAC,CAAC,CAAC,CAAC,CAAC,CAAC,CAAC,CAAC,CAAC,CAAC,CAAC,CAAC,CAAC,CAAC,CAAC,CAAC,CAAC,CAAC,CAAC,CAAC,CAAC,CAAC,CAAC,CAAC,CAAC,CAAC;AAClC,CAAC,CAAC,CAAC,CAAC,CAAC,CAAC,CAAC,CAAC,CAAC,CAAC,CAAC,CAAC,CAAC,CAAC,CAAC,CAAC,CAAC,CAAC,CAAC,CAAC,CAAC,CAAC,CAAC,CAAC,CAAC,CAAC,CAAC,CAAC,CAAC,CAAC,CAAC,CAAC,CAAC,CAAC,CAAC,CAAC,CAAC,CAAC,CAAC,CAAC,CAAC,CAAC,CAAC,CAAC,CAAC,CAAC,CAAC,CAAC,CAAC,CAAC,CAAC,CAAC,CAAC,CAAC,CAAC,CAAC,CAAC,CAAC,CAAC,CAAC,CAAC,CAAC,CAAC,CAAC,CAAC,CAAC,CAAC,CAAC,CAAC,CAAC,CAAC,CAAC,CAAC,CAAC,CAAC,CAAC,CAAC,CAAC,CAAC,CAAC,CAAC,CAAC,CAAC,CAAC,CAAC,CAAC,CAAC,CAAC,CAAC,CAAC,CAAC,CAAC,CAAC,CAAC,CAAC,CAAC,CAAC,CAAC,CAAC,CAAC,CAAC,CAAC,CAAC,CAAC,CAAC,CAAC,CAAC,CAAC,CAAC,CAAC,CAAC,CAAC,CAAC,CAAC,CAAC,CAAC,CAAC,CAAC,CAAC,CAAC,CAAC,CAAC,CAAC,CAAC,CAAC,CAAC,CAAC,CAAC,CAAC,CAAC,CAAC,CAAC;AACpI,CAAC,CAAC,CAAC,CAAC,CAAC,CAAC,CAAC,CAAC,CAAC,CAAC,CAAC,CAAC,CAAC,CAAC,CAAC,CAAC,CAAC,CAAC,CAAC,CAAC,CAAC,CAAC,CAAC,CAAC,CAAC,CAAC,CAAC,CAAC,CAAC,CAAC,CAAC,CAAC,CAAC,CAAC,CAAC,CAAC,CAAC,CAAC,CAAC,CAAC,CAAC,CAAC,CAAC,CAAC,CAAC,CAAC,CAAC,CAAC,CAAC,CAAC,CAAC,CAAC,CAAC,CAAC,CAAC,CAAC,CAAC,CAAC,CAAC,CAAC,CAAC,CAAC,CAAC,CAAC,CAAC,CAAC,CAAC,CAAC,CAAC,CAAC,CAAC,CAAC,CAAC,CAAC,CAAC,CAAC,CAAC,CAAC,CAAC,CAAC,CAAC,CAAC,CAAC,CAAC,CAAC,CAAC,CAAC,CAAC;AACxF;AACA,CAAC,CAAC,CAAC,CAAC,CAAC,CAAC,CAAC,CAAC,CAAC,CAAC,CAAC,CAAC,CAAC,CAAC,CAAC,CAAC,CAAC,CAAC,CAAC;AACnB,CAAC,CAAC,CAAC,CAAC,CAAC,CAAC,CAAC,CAAC,CAAC,CAAC,CAAC,CAAC,CAAC,CAAC,CAAC;AACf,CAAC;AACD;AACA,CAAC,CAAC,CAAC,CAAC,CAAC,CAAC,CAAC,CAAC,CAAC,CAAC,CAAC,CAAC,CAAC,CAAC,CAAC,CAAC,CAAC,CAAC,CAAC,CAAC,CAAC,CAAC,CAAC,CAAC,CAAC,CAAC;AAC1B,CAAC,CAAC,CAAC,CAAC,CAAC,CAAC,CAAC,CAAC,CAAC,CAAC,CAAC,CAAC,CAAC,CAAC,CAAC,CAAC,CAAC,CAAC,CAAC,CAAC,CAAC,CAAC,CAAC,CAAC,CAAC,CAAC,CAAC,CAAC,CAAC,CAAC,CAAC,CAAC,CAAC,CAAC,CAAC,CAAC,CAAC,CAAC,CAAC,CAAC,CAAC,CAAC,CAAC,CAAC,CAAC,CAAC,CAAC,CAAC,CAAC,CAAC,CAAC,CAAC,CAAC,CAAC,CAAC,CAAC,CAAC,CAAC,CAAC,CAAC,CAAC,CAAC,CAAC,CAAC,CAAC,CAAC,CAAC,CAAC,CAAC,CAAC,CAAC,CAAC,CAAC,CAAC,CAAC,CAAC,CAAC,CAAC,CAAC,CAAC,CAAC,CAAC,CAAC,CAAC,CAAC,CAAC,CAAC,CAAC,CAAC,CAAC,CAAC,CAAC,CAAC,CAAC,CAAC,CAAC,CAAC,CAAC,CAAC,CAAC,CAAC;AACrG,CAAC,CAAC,CAAC,CAAC,CAAC,CAAC,CAAC,CAAC,CAAC,CAAC,CAAC,CAAC,CAAC,CAAC,CAAC,CAAC,CAAC,CAAC,CAAC,CAAC,CAAC,CAAC,CAAC,CAAC,CAAC,CAAC,CAAC,CAAC,CAAC,CAAC,CAAC,CAAC,CAAC,CAAC,CAAC,CAAC,CAAC,CAAC,CAAC,CAAC,CAAC,CAAC,CAAC,CAAC,CAAC,CAAC,CAAC,CAAC,CAAC,CAAC,CAAC,CAAC,CAAC,CAAC,CAAC,CAAC,CAAC,CAAC,CAAC,CAAC,CAAC,CAAC,CAAC,CAAC,CAAC,CAAC,CAAC,CAAC,CAAC,CAAC,CAAC,CAAC,CAAC,CAAC,CAAC,CAAC,CAAC,CAAC,CAAC,CAAC,CAAC,CAAC,CAAC,CAAC,CAAC,CAAC,CAAC,CAAC,CAAC,CAAC,CAAC,CAAC,CAAC,CAAC,CAAC,CAAC,CAAC;AACjG,CAAC,CAAC,CAAC,CAAC,CAAC,CAAC,CAAC,CAAC,CAAC,CAAC,CAAC,CAAC,CAAC,CAAC,CAAC,CAAC,CAAC,CAAC,CAAC,CAAC,CAAC,CAAC,CAAC,CAAC,CAAC,CAAC,CAAC,CAAC,CAAC,CAAC,CAAC,CAAC,CAAC,CAAC,CAAC,CAAC,CAAC,CAAC,CAAC,CAAC,CAAC,CAAC,CAAC,CAAC,CAAC,CAAC,CAAC,CAAC,CAAC,CAAC,CAAC,CAAC,CAAC,CAAC,CAAC,CAAC,CAAC,CAAC,CAAC,CAAC,CAAC,CAAC,CAAC,CAAC,CAAC,CAAC,CAAC,CAAC,CAAC,CAAC,CAAC,CAAC,CAAC,CAAC,CAAC,CAAC,CAAC,CAAC,CAAC,CAAC,CAAC,CAAC,CAAC,CAAC,CAAC,CAAC,CAAC,CAAC,CAAC,CAAC,CAAC,CAAC,CAAC,CAAC,CAAC,CAAC,CAAC,CAAC,CAAC,CAAC,CAAC;AACrG,CAAC,CAAC,CAAC,CAAC,CAAC,CAAC,CAAC,CAAC,CAAC,CAAC,CAAC,CAAC,CAAC,CAAC,CAAC,CAAC,CAAC,CAAC,CAAC,CAAC,CAAC,CAAC,CAAC,CAAC,CAAC,CAAC,CAAC,CAAC,CAAC,CAAC,CAAC,CAAC,CAAC,CAAC,CAAC,CAAC,CAAC,CAAC,CAAC,CAAC,CAAC,CAAC,CAAC,CAAC,CAAC,CAAC,CAAC,CAAC,CAAC,CAAC,CAAC,CAAC,CAAC,CAAC,CAAC;AACvD;AACA,CAAC,CAAC,CAAC,CAAC,CAAC,CAAC,CAAC,CAAC,CAAC,CAAC,CAAC,CAAC,CAAC,CAAC,CAAC,CAAC,CAAC,CAAC,CAAC,CAAC,CAAC,CAAC,CAAC,CAAC,CAAC,CAAC,CAAC,CAAC,CAAC,CAAC,CAAC,CAAC,CAAC,CAAC,CAAC,CAAC,CAAC,CAAC,CAAC,CAAC,CAAC,CAAC,CAAC,CAAC,CAAC,CAAC,CAAC,CAAC,CAAC,CAAC,CAAC,CAAC,CAAC,CAAC,CAAC,CAAC,CAAC,CAAC,CAAC,CAAC,CAAC,CAAC;AAC9D,CAAC,CAAC,CAAC,CAAC,CAAC,CAAC,CAAC,CAAC,CAAC,CAAC,CAAC,CAAC,CAAC,CAAC,CAAC,CAAC,CAAC,CAAC,CAAC,CAAC,CAAC,CAAC,CAAC,CAAC,CAAC,CAAC,CAAC,CAAC,CAAC,CAAC,CAAC,CAAC,CAAC,CAAC,CAAC,CAAC,CAAC,CAAC,CAAC,CAAC,CAAC,CAAC,CAAC,CAAC,CAAC,CAAC,CAAC,CAAC,CAAC,CAAC,CAAC,CAAC,CAAC,CAAC,CAAC,CAAC,CAAC,CAAC,CAAC;AAC3D,CAAC,CAAC,CAAC,CAAC,CAAC,CAAC,CAAC,CAAC,CAAC,CAAC,CAAC,CAAC,CAAC,CAAC,CAAC,CAAC,CAAC,CAAC,CAAC,CAAC,CAAC,CAAC,CAAC,CAAC,CAAC,CAAC,CAAC,CAAC,CAAC,CAAC,CAAC,CAAC,CAAC,CAAC,CAAC,CAAC,CAAC;AACrC,CAAC,CAAC,CAAC,CAAC,CAAC,CAAC,CAAC,CAAC,CAAC,CAAC,CAAC,CAAC,CAAC,CAAC,CAAC,CAAC,CAAC,CAAC,CAAC,CAAC,CAAC,CAAC,CAAC,CAAC,CAAC,CAAC,CAAC,CAAC,CAAC,CAAC,CAAC;AAC/B,CAAC,CAAC,CAAC,CAAC,CAAC,CAAC,CAAC,CAAC,CAAC,CAAC,CAAC,CAAC,CAAC,CAAC,CAAC,CAAC,CAAC,CAAC,CAAC,CAAC,CAAC,CAAC,CAAC,CAAC,CAAC,CAAC,CAAC,CAAC,CAAC;AAC7B,CAAC,CAAC,CAAC,CAAC,CAAC,CAAC,CAAC,CAAC,CAAC,CAAC,CAAC,CAAC,CAAC,CAAC,CAAC,CAAC,CAAC,CAAC,CAAC,CAAC,CAAC,CAAC,CAAC,CAAC,CAAC,CAAC,CAAC,CAAC,CAAC,CAAC,CAAC;AAC/B,CAAC,CAAC,CAAC,CAAC,CAAC,CAAC,CAAC,CAAC;AACR,CAAC,CAAC,CAAC,CAAC,CAAC,CAAC,CAAC,CAAC,CAAC,CAAC,CAAC,CAAC,CAAC,CAAC,CAAC,CAAC,CAAC,CAAC,CAAC,CAAC,CAAC,CAAC,CAAC,CAAC,CAAC,CAAC,CAAC,CAAC,CAAC,CAAC,CAAC,CAAC,CAAC,CAAC,CAAC,CAAC,CAAC,CAAC,CAAC,CAAC;AACxC,CAAC,CAAC,CAAC,CAAC,CAAC,CAAC,CAAC,CAAC,CAAC,CAAC,CAAC,CAAC,CAAC,CAAC,CAAC,CAAC,CAAC,CAAC,CAAC,CAAC,CAAC,CAAC,CAAC,CAAC,CAAC,CAAC,CAAC,CAAC,CAAC,CAAC,CAAC,CAAC,CAAC,CAAC,CAAC,CAAC,CAAC,CAAC,CAAC,CAAC,CAAC,CAAC,CAAC,CAAC,CAAC,CAAC,CAAC,CAAC,CAAC,CAAC,CAAC,CAAC,CAAC,CAAC,CAAC,CAAC,CAAC,CAAC,CAAC,CAAC,CAAC,CAAC,CAAC,CAAC,CAAC,CAAC,CAAC,CAAC,CAAC,CAAC,CAAC,CAAC,CAAC,CAAC,CAAC,CAAC,CAAC,CAAC,CAAC,CAAC,CAAC,CAAC,CAAC,CAAC,CAAC,CAAC,CAAC,CAAC,CAAC,CAAC,CAAC,CAAC,CAAC,CAAC,CAAC,CAAC,CAAC,CAAC,CAAC,CAAC,CAAC,CAAC,CAAC,CAAC,CAAC,CAAC,CAAC,CAAC;AAC5G,CAAC,CAAC,CAAC,CAAC,CAAC,CAAC,CAAC,CAAC,CAAC;AACT,CAAC,CAAC,CAAC,CAAC,CAAC,CAAC,CAAC,CAAC,CAAC,CAAC,CAAC,CAAC,CAAC,CAAC,CAAC,CAAC,CAAC,CAAC,CAAC,CAAC,CAAC,CAAC,CAAC,CAAC,CAAC,CAAC,CAAC,CAAC,CAAC,CAAC,CAAC,CAAC,CAAC,CAAC,CAAC,CAAC,CAAC,CAAC,CAAC,CAAC,CAAC,CAAC,CAAC,CAAC;AAC5C,CAAC,CAAC,CAAC,CAAC,CAAC,CAAC,CAAC,CAAC,CAAC,CAAC,CAAC,CAAC,CAAC,CAAC,CAAC,CAAC,CAAC,CAAC,CAAC,CAAC,CAAC,CAAC,CAAC,CAAC,CAAC,CAAC,CAAC,CAAC,CAAC,CAAC,CAAC,CAAC,CAAC,CAAC,CAAC,CAAC,CAAC,CAAC,CAAC,CAAC,CAAC,CAAC,CAAC,CAAC,CAAC,CAAC,CAAC,CAAC,CAAC,CAAC,CAAC,CAAC,CAAC,CAAC,CAAC,CAAC,CAAC,CAAC,CAAC,CAAC,CAAC,CAAC,CAAC,CAAC,CAAC,CAAC,CAAC,CAAC,CAAC,CAAC,CAAC,CAAC;AACxE,CAAC,CAAC,CAAC,CAAC,CAAC,CAAC,CAAC,CAAC,CAAC;AACT,CAAC,CAAC,CAAC,CAAC,CAAC,CAAC,CAAC,CAAC,CAAC,CAAC,CAAC,CAAC,CAAC,CAAC,CAAC,CAAC,CAAC,CAAC,CAAC,CAAC,CAAC,CAAC,CAAC,CAAC,CAAC,CAAC,CAAC,CAAC,CAAC,CAAC,CAAC,CAAC,CAAC,CAAC,CAAC,CAAC,CAAC,CAAC,CAAC,CAAC,CAAC,CAAC;AAC1C,CAAC,CAAC,CAAC,CAAC,CAAC,CAAC,CAAC,CAAC,CAAC,CAAC,CAAC,CAAC,CAAC,CAAC,CAAC,CAAC,CAAC,CAAC,CAAC,CAAC,CAAC,CAAC,CAAC,CAAC,CAAC,CAAC,CAAC,CAAC,CAAC,CAAC,CAAC,CAAC,CAAC,CAAC,CAAC,CAAC,CAAC,CAAC,CAAC,CAAC,CAAC,CAAC,CAAC,CAAC,CAAC,CAAC,CAAC,CAAC,CAAC,CAAC,CAAC,CAAC,CAAC,CAAC,CAAC,CAAC,CAAC,CAAC,CAAC,CAAC,CAAC,CAAC,CAAC,CAAC,CAAC,CAAC,CAAC,CAAC,CAAC,CAAC,CAAC,CAAC,CAAC,CAAC,CAAC,CAAC,CAAC,CAAC,CAAC,CAAC,CAAC,CAAC,CAAC,CAAC,CAAC,CAAC,CAAC,CAAC,CAAC,CAAC,CAAC,CAAC,CAAC,CAAC,CAAC,CAAC,CAAC,CAAC,CAAC,CAAC,CAAC,CAAC,CAAC,CAAC,CAAC,CAAC,CAAC,CAAC,CAAC,CAAC;AAC9G,CAAC,CAAC,CAAC,CAAC,CAAC,CAAC,CAAC,CAAC,CAAC;AACT,CAAC,CAAC,CAAC,CAAC,CAAC,CAAC,CAAC,CAAC,CAAC,CAAC;AACV,CAAC,CAAC,CAAC,CAAC,CAAC,CAAC,CAAC,CAAC,CAAC,CAAC,CAAC,CAAC,CAAC,CAAC,CAAC,CAAC,CAAC,CAAC,CAAC,CAAC,CAAC,CAAC,CAAC,CAAC,CAAC,CAAC,CAAC,CAAC,CAAC,CAAC;AAC9B,CAAC,CAAC,CAAC,CAAC,CAAC,CAAC,CAAC,CAAC,CAAC;AACT,CAAC;AACD,CAAC;AACD;AACA,CAAC;AACD;AACA;AACA;AACA,CAAC,CAAC,CAAC,CAAC,CAAC,CAAC,CAAC,CAAC,CAAC,CAAC,CAAC,CAAC,CAAC,CAAC,CAAC,CAAC,CAAC,CAAC,CAAC,CAAC,CAAC,CAAC,CAAC"
      }
    },
    {
      "name": "unctx:transform",
      "start": 1717261251100,
      "end": 1717261251100,
      "order": "post"
    },
    {
      "name": "nuxt:pages-macros-transform",
      "start": 1717261251100,
      "end": 1717261251100,
      "order": "post"
    },
    {
      "name": "nuxt:runtime-paths-dep",
      "start": 1717261251100,
      "end": 1717261251100,
      "order": "post"
    },
    {
      "name": "nuxt:route-injection-plugin",
      "start": 1717261251100,
      "end": 1717261251100,
      "order": "post"
    },
    {
      "name": "nuxt:components-loader",
      "result": "import { default as __nuxt_component_0 } from \"/media/linux/833cfef0-7984-46f2-8f58-ee0be3a5d0782/DATA/XPS-DATA/DEV/WORKSPACE/PROJECTS/PARTNERSHIPS/IMPERAMAX/OFFERS/nuxt-restaurant-management-system/src/components/dashboard/bookings/modals/Create.vue\";\nimport { default as __nuxt_component_1 } from \"/media/linux/833cfef0-7984-46f2-8f58-ee0be3a5d0782/DATA/XPS-DATA/DEV/WORKSPACE/PROJECTS/PARTNERSHIPS/IMPERAMAX/OFFERS/nuxt-restaurant-management-system/src/components/dashboard/bookings/modals/Edit.vue\";\nimport { default as __nuxt_component_2 } from \"/media/linux/833cfef0-7984-46f2-8f58-ee0be3a5d0782/DATA/XPS-DATA/DEV/WORKSPACE/PROJECTS/PARTNERSHIPS/IMPERAMAX/OFFERS/nuxt-restaurant-management-system/src/components/dashboard/bookings/modals/Delete.vue\";\nimport { default as __nuxt_component_3 } from \"/media/linux/833cfef0-7984-46f2-8f58-ee0be3a5d0782/DATA/XPS-DATA/DEV/WORKSPACE/PROJECTS/PARTNERSHIPS/IMPERAMAX/OFFERS/nuxt-restaurant-management-system/src/node_modules/@nuxt/ui/dist/runtime/components/data/Table.vue\";\nimport { useBookingStore } from '/media/linux/833cfef0-7984-46f2-8f58-ee0be3a5d0782/DATA/XPS-DATA/DEV/WORKSPACE/PROJECTS/PARTNERSHIPS/IMPERAMAX/OFFERS/nuxt-restaurant-management-system/src/stores/bookings.ts';\nimport { resolveComponent as _resolveComponent, createVNode as _createVNode, unref as _unref, toDisplayString as _toDisplayString, createTextVNode as _createTextVNode, withCtx as _withCtx, Fragment as _Fragment, openBlock as _openBlock, createElementBlock as _createElementBlock } from \"vue\"\n\n\nconst _sfc_main = {\n  __name: 'Main',\n  props: {\n  menu: Array,\n  columns: String,\n},\n  setup(__props) {\n\n\n\n\n\nconst bookingStore = useBookingStore()\nlet { bookings } = bookingStore\n\nfunction getMonthName(monthNumber) {\n  const date = new Date();\n  date.setMonth(monthNumber);\n\n  return date.toLocaleString('en-US', { month: 'short' });\n}\n\nfunction datesaregay(date_string){\n  var date = new Date(date_string)\n  var result = \"\" + (date.getDay() + 1) + \"/\" + (date.getMonth() + 1) + \"/\" + date.getFullYear() + \", \" + date.toLocaleTimeString() \n  //var result = \"\" + date.getFullYear() + getMonthName(date.getMonth()) + date.getDay()\n\nconsole.log(result)\n  return result\n}\n\nreturn (_ctx, _cache) => {\n  const _component_DashboardBookingsModalsCreate = __nuxt_component_0\n  const _component_DashboardBookingsModalsEdit = __nuxt_component_1\n  const _component_DashboardBookingsModalsDelete = __nuxt_component_2\n  const _component_UTable = __nuxt_component_3\n\n  return (_openBlock(), _createElementBlock(_Fragment, null, [\n    _createVNode(_component_DashboardBookingsModalsCreate),\n    _createVNode(_component_UTable, {\n      columns: __props.columns,\n      rows: _unref(bookings),\n      sort: { column: 'title' }\n    }, {\n      \"edit-data\": _withCtx(({row}) => [\n        _createVNode(_component_DashboardBookingsModalsEdit, { bookingitem: row }, null, 8, [\"bookingitem\"])\n      ]),\n      \"datetime-data\": _withCtx(({row}) => [\n        _createTextVNode(_toDisplayString(datesaregay(row.datetime)), 1)\n      ]),\n      \"delete-data\": _withCtx(({row}) => [\n        _createVNode(_component_DashboardBookingsModalsDelete, { bookingitem: row }, null, 8, [\"bookingitem\"])\n      ]),\n      _: 1\n    }, 8, [\"columns\", \"rows\"])\n  ], 64))\n}\n}\n\n}\n\n\n\nexport default _sfc_main",
      "start": 1717261251100,
      "end": 1717261251100,
      "order": "post"
    },
    {
      "name": "nuxt:tree-shake-composables:transform",
      "start": 1717261251101,
      "end": 1717261251101,
      "order": "post"
    },
    {
      "name": "vite:build-import-analysis",
      "start": 1717261251101,
      "end": 1717261251101,
      "order": "normal"
    },
    {
      "name": "vite:reporter",
      "start": 1717261251101,
      "end": 1717261251101,
      "order": "normal"
    }
  ]
}
